DESCRIPTION
MANIFEST.in
README
README.rst
setup.py
color_captcha/__init__.py
color_captcha/__init__.pyc
color_captcha/fields.py
color_captcha/settings.py
color_captcha/settings.pyc
color_captcha/utils.py
color_captcha/utils.pyc
color_captcha/widgets.py
color_captcha/static/color_captcha/css/color_captcha.css
color_captcha/templates/color_captcha/widget.html
django_color_captcha.egg-info/PKG-INFO
django_color_captcha.egg-info/SOURCES.txt
django_color_captcha.egg-info/dependency_links.txt
django_color_captcha.egg-info/top_level.txt