Metadata-Version: 1.1
Name: django-color-captcha
Version: 0.1.0
Summary: Simple and pretty user-friendly captcha module for Django framework.
